{
  "_content": {
    "Attributes": {
      "children": [],
      "title": null
    },
    "Extended Summary": {
      "children": [
        {
          "data": {
            "children": [],
            "kind": "versionadded",
            "title": "1.6.0"
          },
          "type": "Admonition"
        }
      ],
      "title": null
    },
    "Methods": {
      "children": [],
      "title": null
    },
    "Notes": {
      "children": [],
      "title": null
    },
    "Other Parameters": {
      "children": [],
      "title": null
    },
    "Parameters": {
      "children": [
        {
          "data": {
            "children": [
              {
                "desc": [
                  {
                    "data": {
                      "children": [
                        {
                          "data": {
                            "value": "The other class must have the "
                          },
                          "type": "Words"
                        },
                        {
                          "data": {
                            "value": [
                              "domain"
                            ]
                          },
                          "type": "Verbatim"
                        },
                        {
                          "data": {
                            "value": " attribute."
                          },
                          "type": "Words"
                        }
                      ]
                    },
                    "type": "Paragraph"
                  }
                ],
                "param": "other",
                "type_": "class instance"
              }
            ]
          },
          "type": "Parameters"
        }
      ],
      "title": null
    },
    "Raises": {
      "children": [],
      "title": null
    },
    "Receives": {
      "children": [],
      "title": null
    },
    "Returns": {
      "children": [
        {
          "data": {
            "children": [
              {
                "desc": [
                  {
                    "data": {
                      "children": [
                        {
                          "data": {
                            "value": "True if the domains are the same, False otherwise."
                          },
                          "type": "Words"
                        }
                      ]
                    },
                    "type": "Paragraph"
                  }
                ],
                "param": "bool",
                "type_": "boolean"
              }
            ]
          },
          "type": "Parameters"
        }
      ],
      "title": null
    },
    "Summary": {
      "children": [
        {
          "data": {
            "children": [
              {
                "data": {
                  "value": "Check if domains match."
                },
                "type": "Words"
              }
            ]
          },
          "type": "Paragraph"
        }
      ],
      "title": null
    },
    "Warnings": {
      "children": [],
      "title": null
    },
    "Warns": {
      "children": [],
      "title": null
    },
    "Yields": {
      "children": [],
      "title": null
    }
  },
  "aliases": [
    "numpy.polynomial._polybase.ABCPolyBase.has_samedomain"
  ],
  "arbitrary": [],
  "example_section_data": {
    "children": [],
    "title": null
  },
  "item_file": "/numpy/polynomial/_polybase.py",
  "item_line": 200,
  "item_type": "<class 'function'>",
  "ordered_sections": [
    "Summary",
    "Extended Summary",
    "Parameters",
    "Returns"
  ],
  "references": null,
  "see_also": [],
  "signature": {
    "value": "has_samedomain(self, other)"
  }
}