{
  "aliases": [
    "scipy.stats._relative_risk.RelativeRiskResult"
  ],
  "arbitrary": [],
  "content": {
    "Attributes": {
      "children": [
        {
          "data": {
            "children": [
              {
                "desc": [
                  {
                    "data": {
                      "children": [
                        {
                          "data": {
                            "value": "This is:      "
                          },
                          "type": "Words"
                        }
                      ]
                    },
                    "type": "Paragraph"
                  },
                  {
                    "data": {
                      "value": "(exposed_cases/exposed_total) / (control_cases/control_total)"
                    },
                    "type": "BlockVerbatim"
                  }
                ],
                "param": "relative_risk",
                "type_": "float"
              },
              {
                "desc": [
                  {
                    "data": {
                      "children": [
                        {
                          "data": {
                            "value": "The number of \"cases\" (i.e. occurrence of disease or other event of interest) among the sample of \"exposed\" individuals."
                          },
                          "type": "Words"
                        }
                      ]
                    },
                    "type": "Paragraph"
                  }
                ],
                "param": "exposed_cases",
                "type_": "int"
              },
              {
                "desc": [
                  {
                    "data": {
                      "children": [
                        {
                          "data": {
                            "value": "The total number of \"exposed\" individuals in the sample."
                          },
                          "type": "Words"
                        }
                      ]
                    },
                    "type": "Paragraph"
                  }
                ],
                "param": "exposed_total",
                "type_": "int"
              },
              {
                "desc": [
                  {
                    "data": {
                      "children": [
                        {
                          "data": {
                            "value": "The number of \"cases\" among the sample of \"control\" or non-exposed individuals."
                          },
                          "type": "Words"
                        }
                      ]
                    },
                    "type": "Paragraph"
                  }
                ],
                "param": "control_cases",
                "type_": "int"
              },
              {
                "desc": [
                  {
                    "data": {
                      "children": [
                        {
                          "data": {
                            "value": "The total number of \"control\" individuals in the sample."
                          },
                          "type": "Words"
                        }
                      ]
                    },
                    "type": "Paragraph"
                  }
                ],
                "param": "control_total",
                "type_": "int"
              }
            ]
          },
          "type": "Parameters"
        }
      ],
      "level": 0,
      "target": null,
      "title": null
    },
    "Extended Summary": {
      "children": [],
      "level": 0,
      "target": null,
      "title": null
    },
    "Methods": {
      "children": [
        {
          "data": {
            "children": [
              {
                "desc": [
                  {
                    "data": {
                      "children": [
                        {
                          "data": {
                            "value": "Compute the confidence interval for the relative risk estimate."
                          },
                          "type": "Words"
                        }
                      ]
                    },
                    "type": "Paragraph"
                  }
                ],
                "param": "confidence_interval",
                "type_": ""
              }
            ]
          },
          "type": "Parameters"
        }
      ],
      "level": 0,
      "target": null,
      "title": null
    },
    "Notes": {
      "children": [],
      "level": 0,
      "target": null,
      "title": null
    },
    "Other Parameters": {
      "children": [],
      "level": 0,
      "target": null,
      "title": null
    },
    "Parameters": {
      "children": [],
      "level": 0,
      "target": null,
      "title": null
    },
    "Raises": {
      "children": [],
      "level": 0,
      "target": null,
      "title": null
    },
    "Receives": {
      "children": [],
      "level": 0,
      "target": null,
      "title": null
    },
    "Returns": {
      "children": [],
      "level": 0,
      "target": null,
      "title": null
    },
    "Summary": {
      "children": [
        {
          "data": {
            "children": [
              {
                "data": {
                  "value": "Result of "
                },
                "type": "Words"
              },
              {
                "data": {
                  "anchor": null,
                  "exists": true,
                  "kind": "module",
                  "reference": {
                    "kind": "api",
                    "module": "scipy",
                    "path": "scipy.stats._relative_risk.relative_risk",
                    "version": "*"
                  },
                  "value": "scipy.stats.contingency.relative_risk"
                },
                "type": "Link"
              },
              {
                "data": {
                  "value": "."
                },
                "type": "Words"
              }
            ]
          },
          "type": "Paragraph"
        }
      ],
      "level": 0,
      "target": null,
      "title": null
    },
    "Warnings": {
      "children": [],
      "level": 0,
      "target": null,
      "title": null
    },
    "Warns": {
      "children": [],
      "level": 0,
      "target": null,
      "title": null
    },
    "Yields": {
      "children": [],
      "level": 0,
      "target": null,
      "title": null
    }
  },
  "example_section_data": {
    "children": [],
    "level": 0,
    "target": null,
    "title": null
  },
  "item_file": "/scipy/stats/_relative_risk.py",
  "item_line": 20,
  "item_type": "<class 'type'>",
  "ordered_sections": [
    "Summary",
    "Attributes",
    "Methods"
  ],
  "references": null,
  "see_also": [],
  "signature": {
    "value": null
  }
}