{
  "_content": {
    "Attributes": {
      "children": [],
      "title": null
    },
    "Extended Summary": {
      "children": [
        {
          "data": {
            "children": [
              {
                "data": {
                  "value": "The derivatives are given by Y0'(z0) = -Y1(z0) at each zero z0."
                },
                "type": "Words"
              }
            ]
          },
          "type": "Paragraph"
        }
      ],
      "title": null
    },
    "Methods": {
      "children": [],
      "title": null
    },
    "Notes": {
      "children": [],
      "title": null
    },
    "Other Parameters": {
      "children": [],
      "title": null
    },
    "Parameters": {
      "children": [
        {
          "data": {
            "children": [
              {
                "desc": [
                  {
                    "data": {
                      "children": [
                        {
                          "data": {
                            "value": "Number of zeros to return"
                          },
                          "type": "Words"
                        }
                      ]
                    },
                    "type": "Paragraph"
                  }
                ],
                "param": "nt",
                "type_": "int"
              },
              {
                "desc": [
                  {
                    "data": {
                      "children": [
                        {
                          "data": {
                            "value": "Set to False to return only the real zeros; set to True to return only the complex zeros with negative real part and positive imaginary part. Note that the complex conjugates of the latter are also zeros of the function, but are not returned by this routine."
                          },
                          "type": "Words"
                        }
                      ]
                    },
                    "type": "Paragraph"
                  }
                ],
                "param": "complex",
                "type_": "bool, default False"
              }
            ]
          },
          "type": "Parameters"
        }
      ],
      "title": null
    },
    "Raises": {
      "children": [],
      "title": null
    },
    "Receives": {
      "children": [],
      "title": null
    },
    "Returns": {
      "children": [
        {
          "data": {
            "children": [
              {
                "desc": [
                  {
                    "data": {
                      "children": [
                        {
                          "data": {
                            "value": "Location of nth zero of Y0(z)"
                          },
                          "type": "Words"
                        }
                      ]
                    },
                    "type": "Paragraph"
                  }
                ],
                "param": "z0n",
                "type_": "ndarray"
              },
              {
                "desc": [
                  {
                    "data": {
                      "children": [
                        {
                          "data": {
                            "value": "Value of derivative Y0'(z0) for nth zero"
                          },
                          "type": "Words"
                        }
                      ]
                    },
                    "type": "Paragraph"
                  }
                ],
                "param": "y0pz0n",
                "type_": "ndarray"
              }
            ]
          },
          "type": "Parameters"
        }
      ],
      "title": null
    },
    "Summary": {
      "children": [
        {
          "data": {
            "children": [
              {
                "data": {
                  "value": "Compute nt zeros of Bessel function Y0(z), and derivative at each zero."
                },
                "type": "Words"
              }
            ]
          },
          "type": "Paragraph"
        }
      ],
      "title": null
    },
    "Warnings": {
      "children": [],
      "title": null
    },
    "Warns": {
      "children": [],
      "title": null
    },
    "Yields": {
      "children": [],
      "title": null
    }
  },
  "aliases": [
    "scipy.signal._filter_design.special.y0_zeros"
  ],
  "arbitrary": [],
  "example_section_data": {
    "children": [],
    "title": null
  },
  "item_file": "/scipy/special/_basic.py",
  "item_line": 497,
  "item_type": "<class 'function'>",
  "ordered_sections": [
    "Summary",
    "Extended Summary",
    "Parameters",
    "Returns",
    "References"
  ],
  "references": null,
  "see_also": [],
  "signature": {
    "value": "y0_zeros(nt, complex=False)"
  }
}