{
  "aliases": [
    "distributed.scheduler.addresses_from_user_args"
  ],
  "arbitrary": [],
  "content": {
    "Attributes": {
      "children": [],
      "level": 0,
      "title": null
    },
    "Extended Summary": {
      "children": [
        {
          "data": {
            "children": [
              {
                "data": {
                  "value": "This is like "
                },
                "type": "Words"
              },
              {
                "data": {
                  "value": [
                    "address_from_user_args"
                  ]
                },
                "type": "Verbatim"
              },
              {
                "data": {
                  "value": " except that it also accepts lists for some of the arguments.  If these arguments are lists then it will map over them accordingly."
                },
                "type": "Words"
              }
            ]
          },
          "type": "Paragraph"
        }
      ],
      "level": 0,
      "title": null
    },
    "Methods": {
      "children": [],
      "level": 0,
      "title": null
    },
    "Notes": {
      "children": [],
      "level": 0,
      "title": null
    },
    "Other Parameters": {
      "children": [],
      "level": 0,
      "title": null
    },
    "Parameters": {
      "children": [],
      "level": 0,
      "title": null
    },
    "Raises": {
      "children": [],
      "level": 0,
      "title": null
    },
    "Receives": {
      "children": [],
      "level": 0,
      "title": null
    },
    "Returns": {
      "children": [],
      "level": 0,
      "title": null
    },
    "Summary": {
      "children": [
        {
          "data": {
            "children": [
              {
                "data": {
                  "value": "Get a list of addresses if the inputs are lists"
                },
                "type": "Words"
              }
            ]
          },
          "type": "Paragraph"
        }
      ],
      "level": 0,
      "title": null
    },
    "Warnings": {
      "children": [],
      "level": 0,
      "title": null
    },
    "Warns": {
      "children": [],
      "level": 0,
      "title": null
    },
    "Yields": {
      "children": [],
      "level": 0,
      "title": null
    }
  },
  "example_section_data": {
    "children": [
      {
        "data": {
          "ce_status": "compiled",
          "entries": [
            {
              "link": {
                "data": {
                  "exists": true,
                  "kind": "module",
                  "reference": {
                    "kind": "module",
                    "module": "distributed",
                    "path": "distributed.comm.addressing.addresses_from_user_args",
                    "version": "2021.10.0"
                  },
                  "value": "addresses_from_user_args"
                },
                "type": "Link"
              },
              "type": ""
            },
            {
              "link": {
                "data": "(",
                "type": "str"
              },
              "type": ""
            },
            {
              "link": {
                "data": "host",
                "type": "str"
              },
              "type": ""
            },
            {
              "link": {
                "data": "=",
                "type": "str"
              },
              "type": "o"
            },
            {
              "link": {
                "data": "\"",
                "type": "str"
              },
              "type": "s2"
            },
            {
              "link": {
                "data": "127.0.0.1",
                "type": "str"
              },
              "type": "s2"
            },
            {
              "link": {
                "data": "\"",
                "type": "str"
              },
              "type": "s2"
            },
            {
              "link": {
                "data": ",",
                "type": "str"
              },
              "type": ""
            },
            {
              "link": {
                "data": " ",
                "type": "str"
              },
              "type": ""
            },
            {
              "link": {
                "data": "protocol",
                "type": "str"
              },
              "type": ""
            },
            {
              "link": {
                "data": "=",
                "type": "str"
              },
              "type": "o"
            },
            {
              "link": {
                "data": "[",
                "type": "str"
              },
              "type": ""
            },
            {
              "link": {
                "data": "\"",
                "type": "str"
              },
              "type": "s2"
            },
            {
              "link": {
                "data": "inproc",
                "type": "str"
              },
              "type": "s2"
            },
            {
              "link": {
                "data": "\"",
                "type": "str"
              },
              "type": "s2"
            },
            {
              "link": {
                "data": ",",
                "type": "str"
              },
              "type": ""
            },
            {
              "link": {
                "data": " ",
                "type": "str"
              },
              "type": ""
            },
            {
              "link": {
                "data": "\"",
                "type": "str"
              },
              "type": "s2"
            },
            {
              "link": {
                "data": "tcp",
                "type": "str"
              },
              "type": "s2"
            },
            {
              "link": {
                "data": "\"",
                "type": "str"
              },
              "type": "s2"
            },
            {
              "link": {
                "data": "]",
                "type": "str"
              },
              "type": ""
            },
            {
              "link": {
                "data": ")",
                "type": "str"
              },
              "type": ""
            }
          ],
          "out": "[\"inproc://127.0.0.1:\", \"tcp://127.0.0.1:\"]"
        },
        "type": "Code2"
      }
    ],
    "level": 0,
    "title": null
  },
  "item_file": "/distributed/comm/addressing.py",
  "item_line": 219,
  "item_type": "<class 'function'>",
  "ordered_sections": [
    "Summary",
    "Extended Summary",
    "Examples"
  ],
  "references": null,
  "see_also": [],
  "signature": {
    "value": "addresses_from_user_args(host=None, port=None, interface=None, protocol=None, peer=None, security=None, default_port=0) -> 'list'"
  }
}