{
  "_content": {
    "Attributes": {
      "children": [],
      "title": null
    },
    "Extended Summary": {
      "children": [],
      "title": null
    },
    "Methods": {
      "children": [],
      "title": null
    },
    "Notes": {
      "children": [],
      "title": null
    },
    "Other Parameters": {
      "children": [],
      "title": null
    },
    "Parameters": {
      "children": [],
      "title": null
    },
    "Raises": {
      "children": [],
      "title": null
    },
    "Receives": {
      "children": [],
      "title": null
    },
    "Returns": {
      "children": [
        {
          "data": {
            "children": [
              {
                "desc": [
                  {
                    "data": {
                      "children": [
                        {
                          "data": {
                            "value": "Return type is the same as the original object with "
                          },
                          "type": "Words"
                        },
                        {
                          "data": {
                            "value": [
                              "np.float64"
                            ]
                          },
                          "type": "Verbatim"
                        },
                        {
                          "data": {
                            "value": " dtype."
                          },
                          "type": "Words"
                        }
                      ]
                    },
                    "type": "Paragraph"
                  }
                ],
                "param": "",
                "type_": "Series or DataFrame"
              }
            ]
          },
          "type": "Parameters"
        }
      ],
      "title": null
    },
    "Summary": {
      "children": [
        {
          "data": {
            "children": [
              {
                "data": {
                  "value": "Calculate the expanding count of non NaN observations."
                },
                "type": "Words"
              }
            ]
          },
          "type": "Paragraph"
        }
      ],
      "title": null
    },
    "Warnings": {
      "children": [],
      "title": null
    },
    "Warns": {
      "children": [],
      "title": null
    },
    "Yields": {
      "children": [],
      "title": null
    }
  },
  "aliases": [
    "pandas.core.generic.Expanding.count"
  ],
  "arbitrary": [],
  "example_section_data": {
    "children": [],
    "title": null
  },
  "item_file": "/pandas/core/window/expanding.py",
  "item_line": 183,
  "item_type": "<class 'function'>",
  "ordered_sections": [
    "Summary",
    "Returns",
    "See Also"
  ],
  "references": null,
  "refs": [
    "pandas.DataFrame.count",
    "pandas.DataFrame.expanding",
    "pandas.Series.count",
    "pandas.Series.expanding"
  ],
  "see_also": [
    {
      "descriptions": [
        {
          "children": [
            {
              "data": {
                "value": "Calling expanding with Series data."
              },
              "type": "Words"
            }
          ]
        }
      ],
      "name": {
        "exists": null,
        "name": "pandas.Series.expanding",
        "ref": "pandas.core.generic.NDFrame.expanding"
      },
      "type": null
    },
    {
      "descriptions": [
        {
          "children": [
            {
              "data": {
                "value": "Calling expanding with DataFrames."
              },
              "type": "Words"
            }
          ]
        }
      ],
      "name": {
        "exists": null,
        "name": "pandas.DataFrame.expanding",
        "ref": "pandas.core.generic.NDFrame.expanding"
      },
      "type": null
    },
    {
      "descriptions": [
        {
          "children": [
            {
              "data": {
                "value": "Aggregating count for Series."
              },
              "type": "Words"
            }
          ]
        }
      ],
      "name": {
        "exists": true,
        "name": "pandas.Series.count",
        "ref": "pandas.core.series.Series.count"
      },
      "type": null
    },
    {
      "descriptions": [
        {
          "children": [
            {
              "data": {
                "value": "Aggregating count for DataFrame."
              },
              "type": "Words"
            }
          ]
        }
      ],
      "name": {
        "exists": true,
        "name": "pandas.DataFrame.count",
        "ref": "pandas.core.frame.DataFrame.count"
      },
      "type": null
    }
  ],
  "signature": {
    "value": "count(self)"
  }
}